catalyst_rl/__init__.py
catalyst_rl/__version__.py
catalyst_rl/contrib/__init__.py
catalyst_rl/contrib/__main__.py
catalyst_rl/contrib/registry.py
catalyst_rl/contrib/data/__init__.py
catalyst_rl/contrib/data/cv/__init__.py
catalyst_rl/contrib/data/cv/mixins/__init__.py
catalyst_rl/contrib/data/cv/mixins/blur.py
catalyst_rl/contrib/data/cv/mixins/flare.py
catalyst_rl/contrib/data/cv/mixins/rotate.py
catalyst_rl/contrib/data/cv/mixins/tests/__init__.py
catalyst_rl/contrib/data/cv/mixins/tests/test_mixin.py
catalyst_rl/contrib/data/cv/transforms/__init__.py
catalyst_rl/contrib/data/cv/transforms/tensor.py
catalyst_rl/contrib/data/nlp/__init__.py
catalyst_rl/contrib/data/nlp/classification/__init__.py
catalyst_rl/contrib/data/nlp/classification/dataset.py
catalyst_rl/contrib/data/nlp/classification/tests/__init__.py
catalyst_rl/contrib/data/nlp/classification/tests/test_text_clf_dataset.py
catalyst_rl/contrib/dl/__init__.py
catalyst_rl/contrib/dl/callbacks/__init__.py
catalyst_rl/contrib/dl/callbacks/alchemy.py
catalyst_rl/contrib/dl/callbacks/criterion.py
catalyst_rl/contrib/dl/callbacks/cutmix_callback.py
catalyst_rl/contrib/dl/callbacks/knn.py
catalyst_rl/contrib/dl/callbacks/neptune.py
catalyst_rl/contrib/dl/callbacks/telegram_logger.py
catalyst_rl/contrib/dl/experiment/__init__.py
catalyst_rl/contrib/dl/runner/__init__.py
catalyst_rl/contrib/dl/runner/alchemy.py
catalyst_rl/contrib/dl/runner/neptune.py
catalyst_rl/contrib/dl/runner/wandb.py
catalyst_rl/contrib/models/__init__.py
catalyst_rl/contrib/models/functional.py
catalyst_rl/contrib/models/sequential.py
catalyst_rl/contrib/models/cv/__init__.py
catalyst_rl/contrib/models/cv/classification/__init__.py
catalyst_rl/contrib/models/cv/classification/mobilenetv2.py
catalyst_rl/contrib/models/cv/classification/mobilenetv3.py
catalyst_rl/contrib/models/cv/encoders/__init__.py
catalyst_rl/contrib/models/cv/encoders/_mobilenetv2.py
catalyst_rl/contrib/models/cv/encoders/mobilenetv2.py
catalyst_rl-20.3.dist-info/LICENSE
catalyst_rl-20.3.dist-info/METADATA
catalyst_rl-20.3.dist-info/WHEEL
catalyst_rl-20.3.dist-info/entry_points.txt
catalyst_rl-20.3.dist-info/top_level.txt
catalyst_rl-20.3.dist-info/RECORD
