Metadata-Version: 2.1
Name: catalyst-rl
Version: 20.3
Summary: Catalyst.RL. PyTorch framework for RL research.
Home-page: https://github.com/catalyst-team/catalyst-rl
Author: Sergey Kolesnikov
Author-email: scitator@gmail.com
License: Apache License 2.0
Download-URL: https://github.com/catalyst-team/catalyst-rl
Project-URL: Bug Tracker, https://github.com/catalyst-team/catalyst-rl/issues
Project-URL: Documentation, https://catalyst-team.github.io/catalyst
Project-URL: Source Code, https://github.com/catalyst-team/catalyst-rl
Keywords: Machine Learning,Distributed Computing,Deep Learning,Reinforcement Learning,PyTorch
Platform: UNKNOWN
Classifier: Environment :: Console
Classifier: Natural Language :: English
Classifier: Development Status :: 4 - Beta
Classifier: Operating System :: OS Independent
Classifier: License :: OSI Approved :: Apache Software License
Classifier: Intended Audience :: Developers
Classifier: Intended Audience :: Science/Research
Classifier: Topic :: Scientific/Engineering :: Artificial Intelligence
Classifier: Topic :: Scientific/Engineering :: Information Analysis
Classifier: Programming Language :: Python
Classifier: Programming Language :: Python :: 3.6
Classifier: Programming Language :: Python :: 3.7
Classifier: Programming Language :: Python :: Implementation :: CPython
Requires-Python: >=3.6.0
Requires-Dist: numpy (>=1.16.4)
Requires-Dist: torch (>=1.0.0)
Requires-Dist: torchvision (>=0.2.1)
Requires-Dist: Pillow (<7)
Requires-Dist: imageio
Requires-Dist: opencv-python
Requires-Dist: scikit-image (>=0.14.2)
Requires-Dist: tqdm (>=4.33.0)
Requires-Dist: PyYAML
Requires-Dist: tensorboard (>=1.14.0)
Requires-Dist: tensorboardX
Requires-Dist: plotly (>=4.1.0)
Requires-Dist: crc32c (>=1.7)
Requires-Dist: ipython
Requires-Dist: packaging
Requires-Dist: deprecation
Requires-Dist: matplotlib
Requires-Dist: seaborn
Requires-Dist: pandas (>=0.22)
Requires-Dist: scikit-learn (>=0.20)
Requires-Dist: GitPython (>=2.1.11)
Requires-Dist: redis
Requires-Dist: pymongo
Requires-Dist: pyarrow (==0.15.1)
Requires-Dist: lz4
Requires-Dist: gym (>=0.13.0)
Requires-Dist: reaction
